connectors/redis.py
ml/__init__.py
ml/jinja_functions.py
ml/train_customer_segmentation.py
ml/train_telco_churn.py
ml/models/registry.json
models/dashboards_sample.yml
models/exposures.yml
models/sources.example.yml
models/sources.yml
models/bronze/stg_campaigns.sql
models/bronze/stg_carriers.sql
models/bronze/stg_commissions.sql
models/bronze/stg_customers.sql
models/bronze/stg_employees.sql
models/bronze/stg_order_items.sql
models/bronze/stg_orders.sql
models/bronze/stg_payment_transactions.sql
models/bronze/stg_products.sql
models/bronze/stg_promotions.sql
models/bronze/stg_purchase_orders.sql
models/bronze/stg_returns.sql
models/bronze/stg_shipments.sql
models/bronze/stg_stock_levels.sql
models/bronze/stg_suppliers.sql
models/bronze/stg_warehouses.sql
models/examples/example_asset_usage.sql
models/gold/fct_customer_returns.sql
models/gold/fct_inventory_metrics.sql
models/gold/fct_marketing_roi.sql
models/gold/fct_orders.sql
models/gold/fct_sales_performance.sql
models/gold/fct_shipping_logistics.sql
models/silver/int_campaign_performance.sql
models/silver/int_customer_orders.sql
models/silver/int_employee_performance.sql
models/silver/int_inventory_summary.sql
models/silver/int_order_details.sql
models/silver/int_payment_reconciliation.sql
models/silver/int_promo_utilization.sql
models/silver/int_return_analysis.sql
models/silver/int_sales_commissions.sql
models/silver/int_shipment_tracking.sql
models/silver/int_supplier_orders.sql
orchestration/__init__.py
orchestration/engine.py
orchestration/history.py
transformations/__init__.py
transformations/dag.py
transformations/model.py
transformations/model_loader.py
transformdash-1.0.1.dist-info/licenses/LICENSE
ui/app.py
ui/app_old_backup.py
ui/static/favicon.png
ui/static/logo-512.png
ui/static/logo-attempt.jpg
ui/static/logo-clean.jpg
ui/static/logo-white.png
ui/static/logo.svg
ui/static/logo2-1024-flat.png
ui/static/logo2-512-flat.png
ui/static/logo2-512.png
ui/static/logo2.jpg
ui/static/logo2.svg
ui/static/css/enhancements.css
ui/static/css/styles.css
transformdash-1.0.1.dist-info/METADATA
transformdash-1.0.1.dist-info/WHEEL
transformdash-1.0.1.dist-info/entry_points.txt
transformdash-1.0.1.dist-info/top_level.txt
transformdash-1.0.1.dist-info/RECORD
