Metadata-Version: 2.4
Name: transformdash
Version: 1.0.1
Summary: A modern, dbt-inspired data transformation platform with ML integration
Home-page: https://github.com/kraftaa/transformdash
Author: Maria Dubyaga
Author-email: Maria Dubyaga <kraftaa@gmail.com>
Maintainer-email: Maria Dubyaga <kraftaa@gmail.com>
License: MIT
Project-URL: Homepage, https://github.com/kraftaa/transformdash
Project-URL: Documentation, https://github.com/kraftaa/transformdash/wiki
Project-URL: Repository, https://github.com/kraftaa/transformdash
Project-URL: Bug Tracker, https://github.com/kraftaa/transformdash/issues
Keywords: data,transformation,etl,dbt,sql,analytics,dashboard,visualization,machine-learning,ml,postgres,fastapi
Classifier: Development Status :: 4 - Beta
Classifier: Intended Audience :: Developers
Classifier: Intended Audience :: Science/Research
Classifier: Topic :: Database
Classifier: Topic :: Scientific/Engineering :: Artificial Intelligence
Classifier: Topic :: Software Development :: Libraries :: Python Modules
Classifier: License :: OSI Approved :: MIT License
Classifier: Programming Language :: Python :: 3
Classifier: Programming Language :: Python :: 3.9
Classifier: Programming Language :: Python :: 3.10
Classifier: Programming Language :: Python :: 3.11
Classifier: Programming Language :: Python :: 3.12
Classifier: Operating System :: OS Independent
Requires-Python: >=3.9
License-File: LICENSE
Requires-Dist: psycopg2-binary>=2.9.6
Requires-Dist: pymongo>=4.4.0
Requires-Dist: redis>=4.5.1
Requires-Dist: sqlalchemy>=2.0.15
Requires-Dist: python-dotenv>=1.0.0
Requires-Dist: fastapi>=0.95.2
Requires-Dist: uvicorn>=0.23.1
Requires-Dist: python-multipart>=0.0.20
Requires-Dist: python-jose[cryptography]>=3.3.0
Requires-Dist: bcrypt>=4.0.1
Requires-Dist: jinja2>=3.1.0
Requires-Dist: pyyaml>=6.0
Requires-Dist: pandas>=2.0.2
Requires-Dist: numpy>=1.20.0
Requires-Dist: faker>=18.10.1
Requires-Dist: apscheduler>=3.10.4
Requires-Dist: scikit-learn>=1.3.0
Requires-Dist: joblib>=1.3.0
Provides-Extra: dev
Requires-Dist: pytest>=7.4.0; extra == "dev"
Requires-Dist: pytest-cov>=4.1.0; extra == "dev"
Requires-Dist: black>=23.0.0; extra == "dev"
Requires-Dist: flake8>=6.0.0; extra == "dev"
Requires-Dist: mypy>=1.0.0; extra == "dev"
Requires-Dist: isort>=5.12.0; extra == "dev"
Provides-Extra: scraping
Requires-Dist: selenium>=4.15.0; extra == "scraping"
Requires-Dist: webdriver-manager>=4.0.1; extra == "scraping"
Requires-Dist: beautifulsoup4>=4.12.0; extra == "scraping"
Requires-Dist: openpyxl>=3.1.2; extra == "scraping"
Provides-Extra: orchestration
Requires-Dist: celery>=5.3.1; extra == "orchestration"
Requires-Dist: prefect>=2.7.9; extra == "orchestration"
Provides-Extra: bigdata
Requires-Dist: pyspark>=3.5.1; extra == "bigdata"
Provides-Extra: ml
Requires-Dist: scikit-learn>=1.3.0; extra == "ml"
Requires-Dist: joblib>=1.3.0; extra == "ml"
Requires-Dist: xgboost>=1.7.0; extra == "ml"
Requires-Dist: lightgbm>=4.0.0; extra == "ml"
Provides-Extra: docs
Requires-Dist: mkdocs>=1.5.0; extra == "docs"
Requires-Dist: mkdocs-material>=9.0.0; extra == "docs"
Requires-Dist: mkdocstrings[python]>=0.22.0; extra == "docs"
Dynamic: author
Dynamic: home-page
Dynamic: license-file
Dynamic: requires-python
